piewuita/__init__.py
piewuita/create_project.py
piewuita/templates/.gitignore
piewuita-0.1.1.dist-info/LICENSE
piewuita-0.1.1.dist-info/METADATA
piewuita-0.1.1.dist-info/WHEEL
piewuita-0.1.1.dist-info/entry_points.txt
piewuita-0.1.1.dist-info/top_level.txt
piewuita-0.1.1.dist-info/RECORD
