Metadata-Version: 2.1
Name: piewuita
Version: 0.1.1
Summary: Init project python
Home-page: https://github.com/Fuan200/
Author: Juan Díaz
Author-email: juandiazfdez1992@gmail.com
Classifier: Programming Language :: Python :: 3
Classifier: License :: OSI Approved :: GNU General Public License v3 (GPLv3)
Classifier: Operating System :: OS Independent
License-File: LICENSE
